scheduler_cpp.cpython-313-darwin.so
os_scheduler_atlas/__init__.py
os_scheduler_atlas/scheduler.py
os_scheduler_atlas-0.2.1.dist-info/METADATA
os_scheduler_atlas-0.2.1.dist-info/WHEEL
os_scheduler_atlas-0.2.1.dist-info/top_level.txt
os_scheduler_atlas-0.2.1.dist-info/RECORD
