Metadata-Version: 2.4
Name: os-scheduler-atlas
Version: 0.2.1
Summary: OS Scheduling Algorithms with ML Prediction
Author: Will Swinson
Author-email: Will Swinson <will.swinson@the10xdevelopers.com>
License-Expression: MIT
Project-URL: Homepage, https://github.com/Will-Swinson/os-scheduler-atlas
Classifier: Development Status :: 3 - Alpha
Classifier: Intended Audience :: Education
Classifier: Programming Language :: Python :: 3
Classifier: Programming Language :: C++
Requires-Python: >=3.8
Requires-Dist: pybind11>=2.6.0
Dynamic: author
Dynamic: requires-python
